stemmer_madura/__init__.py
stemmer_madura/stemmer.py
stemmer_madura/data/lemmawords.txt
stemmer_madura/data/stopwords.txt
stemmer_madura/lib/__init__.py
stemmer_madura/lib/ngram.py
stemmer_madura/lib/rules.py
stemmer_madura/lib/stemmer.py
stemmer_madura-0.1.8.dist-info/LICENSE
stemmer_madura-0.1.8.dist-info/METADATA
stemmer_madura-0.1.8.dist-info/WHEEL
stemmer_madura-0.1.8.dist-info/top_level.txt
stemmer_madura-0.1.8.dist-info/RECORD
