Metadata-Version: 2.1
Name: stemmer-madura
Version: 0.1.8
Summary: Stemmer untuk bahasa Madura menggunakan rule based
Author: Mohammad Nazir Arifin
Author-email: Mohammad Nazir Arifin <ceylon.rizan@gmail.com>
License: MIT License
Project-URL: Homepage, https://github.com/NazirArifin/stemmer-madura-py
Project-URL: Bug Tracker, https://github.com/NazirArifin/stemmer-madura-py/issues
Keywords: stemmer,madura,bahasa madura,nlp
Classifier: Programming Language :: Python :: 3
Classifier: License :: OSI Approved :: MIT License
Classifier: Operating System :: OS Independent
Requires-Python: >=3.7
License-File: LICENSE
